{
	"info": {
		"_postman_id": "unified-faith-service-islamic-api",
		"name": "Unified Faith Service - Islamic API",
		"description": "API collection for Unified Faith Service Islamic features including Prayer Times, Quran, Dhikr, Qibla, and Calendar.",
		"schema": "https://schema.getpostman.com/json/collection/v2.1.0/collection.json"
	},
	"item": [
		{
			"name": "Metadata",
			"item": [
				{
					"name": "Get Supported Faiths",
					"request": {
						"method": "GET",
						"header": [],
						"url": {
							"raw": "{{baseUrl}}/api/v1/faiths",
							"host": ["{{baseUrl}}"],
							"path": ["api", "v1", "faiths"]
						}
					},
					"response": []
				}
			]
		},
		{
			"name": "Auth",
			"item": [
				{
					"name": "Login",
					"event": [
						{
							"listen": "test",
							"script": {
								"exec": [
									"var jsonData = pm.response.json();",
									"if (jsonData.accessToken) {",
									"    pm.environment.set(\"token\", jsonData.accessToken);",
									"    console.log(\"Token updated\");",
									"}",
									"if (jsonData.access_token) {",
									"    pm.environment.set(\"token\", jsonData.access_token);",
									"    console.log(\"Token updated (access_token format)\");",
									"}"
								],
								"type": "text/javascript"
							}
						}
					],
					"request": {
						"method": "POST",
						"header": [],
						"body": {
							"mode": "raw",
							"raw": "{\n    \"email\": \"arhamimam2000@gmail.com\",\n    \"password\": \"Admin@1099\"\n}",
							"options": {
								"raw": {
									"language": "json"
								}
							}
						},
						"url": {
							"raw": "{{baseUrl}}/auth/login",
							"host": ["{{baseUrl}}"],
							"path": ["auth", "login"]
						}
					},
					"response": []
				},
				{
					"name": "Register",
					"event": [
						{
							"listen": "test",
							"script": {
								"exec": [
									"var jsonData = pm.response.json();",
									"if (jsonData.accessToken) {",
									"    pm.environment.set(\"token\", jsonData.accessToken);",
									"    pm.environment.set(\"refreshToken\", jsonData.refreshToken || jsonData.refresh_token);",
									"}",
									"if (jsonData.access_token) {",
									"    pm.environment.set(\"token\", jsonData.access_token);",
									"    pm.environment.set(\"refreshToken\", jsonData.refresh_token);",
									"}"
								],
								"type": "text/javascript"
							}
						}
					],
					"request": {
						"method": "POST",
						"header": [],
						"body": {
							"mode": "raw",
							"raw": "{\n    \"email\": \"testuser@example.com\",\n    \"password\": \"Test@1234\",\n    \"fullName\": \"Test User\"\n}",
							"options": {
								"raw": {
									"language": "json"
								}
							}
						},
						"url": {
							"raw": "{{baseUrl}}/auth/register",
							"host": ["{{baseUrl}}"],
							"path": ["auth", "register"]
						}
					},
					"response": []
				},
				{
					"name": "Request OTP",
					"request": {
						"method": "POST",
						"header": [],
						"body": {
							"mode": "raw",
							"raw": "{\n    \"email\": \"arhamimam2000@gmail.com\"\n}",
							"options": {
								"raw": {
									"language": "json"
								}
							}
						},
						"url": {
							"raw": "{{baseUrl}}/auth/login/request-otp",
							"host": ["{{baseUrl}}"],
							"path": ["auth", "login", "request-otp"]
						}
					},
					"response": []
				},
				{
					"name": "Verify OTP",
					"event": [
						{
							"listen": "test",
							"script": {
								"exec": [
									"var jsonData = pm.response.json();",
									"if (jsonData.accessToken) {",
									"    pm.environment.set(\"token\", jsonData.accessToken);",
									"    pm.environment.set(\"refreshToken\", jsonData.refreshToken || jsonData.refresh_token);",
									"}",
									"if (jsonData.access_token) {",
									"    pm.environment.set(\"token\", jsonData.access_token);",
									"    pm.environment.set(\"refreshToken\", jsonData.refresh_token);",
									"}"
								],
								"type": "text/javascript"
							}
						}
					],
					"request": {
						"method": "POST",
						"header": [],
						"body": {
							"mode": "raw",
							"raw": "{\n    \"email\": \"arhamimam2000@gmail.com\",\n    \"otp\": \"123456\"\n}",
							"options": {
								"raw": {
									"language": "json"
								}
							}
						},
						"url": {
							"raw": "{{baseUrl}}/auth/login/verify-otp",
							"host": ["{{baseUrl}}"],
							"path": ["auth", "login", "verify-otp"]
						}
					},
					"response": []
				},
				{
					"name": "Refresh Token",
					"event": [
						{
							"listen": "test",
							"script": {
								"exec": [
									"var jsonData = pm.response.json();",
									"if (jsonData.accessToken) {",
									"    pm.environment.set(\"token\", jsonData.accessToken);",
									"    pm.environment.set(\"refreshToken\", jsonData.refreshToken || jsonData.refresh_token);",
									"}",
									"if (jsonData.access_token) {",
									"    pm.environment.set(\"token\", jsonData.access_token);",
									"    pm.environment.set(\"refreshToken\", jsonData.refresh_token);",
									"}"
								],
								"type": "text/javascript"
							}
						}
					],
					"request": {
						"method": "POST",
						"header": [],
						"body": {
							"mode": "raw",
							"raw": "{\n    \"refresh_token\": \"{{refreshToken}}\"\n}",
							"options": {
								"raw": {
									"language": "json"
								}
							}
						},
						"url": {
							"raw": "{{baseUrl}}/auth/refresh",
							"host": ["{{baseUrl}}"],
							"path": ["auth", "refresh"]
						}
					},
					"response": []
				},
				{
					"name": "Logout",
					"request": {
						"auth": {
							"type": "bearer",
							"bearer": [
								{
									"key": "token",
									"value": "{{token}}",
									"type": "string"
								}
							]
						},
						"method": "POST",
						"header": [],
						"body": {
							"mode": "raw",
							"raw": "{\n    \"refresh_token\": \"{{refreshToken}}\"\n}",
							"options": {
								"raw": {
									"language": "json"
								}
							}
						},
						"url": {
							"raw": "{{baseUrl}}/auth/logout",
							"host": ["{{baseUrl}}"],
							"path": ["auth", "logout"]
						}
					},
					"response": []
				},
				{
					"name": "Get Profile",
					"request": {
						"auth": {
							"type": "bearer",
							"bearer": [
								{
									"key": "token",
									"value": "{{token}}",
									"type": "string"
								}
							]
						},
						"method": "GET",
						"header": [],
						"url": {
							"raw": "{{baseUrl}}/auth/profile",
							"host": ["{{baseUrl}}"],
							"path": ["auth", "profile"]
						}
					},
					"response": []
				},
				{
					"name": "Validate Token",
					"request": {
						"auth": {
							"type": "bearer",
							"bearer": [
								{
									"key": "token",
									"value": "{{token}}",
									"type": "string"
								}
							]
						},
						"method": "GET",
						"header": [],
						"url": {
							"raw": "{{baseUrl}}/auth/validate",
							"host": ["{{baseUrl}}"],
							"path": ["auth", "validate"]
						}
					},
					"response": []
				}
			]
		},
		{
			"name": "Calendar",
			"item": [
				{
					"name": "Get Today's Date",
					"request": {
						"method": "GET",
						"header": [],
						"url": {
							"raw": "{{baseUrl}}/api/v1/islam/calendar/today",
							"host": ["{{baseUrl}}"],
							"path": ["api", "v1", "islam", "calendar", "today"],
							"query": [
								{
									"key": "timezone",
									"value": "Asia/Kolkata",
									"description": "IANA timezone (optional)",
									"disabled": true
								}
							]
						}
					},
					"response": []
				},
				{
					"name": "Get Today's Date (New York)",
					"request": {
						"method": "GET",
						"header": [],
						"url": {
							"raw": "{{baseUrl}}/api/v1/islam/calendar/today?timezone=America/New_York",
							"host": ["{{baseUrl}}"],
							"path": ["api", "v1", "islam", "calendar", "today"],
							"query": [
								{
									"key": "timezone",
									"value": "America/New_York"
								}
							]
						}
					},
					"response": []
				},
				{
					"name": "Convert Gregorian to Hijri",
					"request": {
						"method": "GET",
						"header": [],
						"url": {
							"raw": "{{baseUrl}}/api/v1/islam/calendar/convert/to-hijri?date=2026-02-15",
							"host": ["{{baseUrl}}"],
							"path": ["api", "v1", "islam", "calendar", "convert", "to-hijri"],
							"query": [
								{
									"key": "date",
									"value": "2026-02-15"
								},
								{
									"key": "timezone",
									"value": "Asia/Kolkata",
									"description": "IANA timezone (optional)",
									"disabled": true
								}
							]
						}
					},
					"response": []
				},
				{
					"name": "Convert Hijri to Gregorian",
					"request": {
						"method": "GET",
						"header": [],
						"url": {
							"raw": "{{baseUrl}}/api/v1/islam/calendar/convert/to-gregorian?year=1447&month=8&day=27",
							"host": ["{{baseUrl}}"],
							"path": ["api", "v1", "islam", "calendar", "convert", "to-gregorian"],
							"query": [
								{
									"key": "year",
									"value": "1447"
								},
								{
									"key": "month",
									"value": "8"
								},
								{
									"key": "day",
									"value": "27"
								},
								{
									"key": "timezone",
									"value": "Asia/Dubai",
									"description": "IANA timezone (optional)",
									"disabled": true
								}
							]
						}
					},
					"response": []
				},
				{
					"name": "Get Gregorian Month Calendar",
					"request": {
						"method": "GET",
						"header": [],
						"url": {
							"raw": "{{baseUrl}}/api/v1/islam/calendar/gregorian-month?year=2026&month=2",
							"host": ["{{baseUrl}}"],
							"path": ["api", "v1", "islam", "calendar", "gregorian-month"],
							"query": [
								{
									"key": "year",
									"value": "2026"
								},
								{
									"key": "month",
									"value": "2"
								},
								{
									"key": "timezone",
									"value": "Asia/Riyadh",
									"description": "IANA timezone (optional)",
									"disabled": true
								}
							]
						}
					},
					"response": []
				},
				{
					"name": "Get Hijri Month Calendar (Ramadan 1447)",
					"request": {
						"method": "GET",
						"header": [],
						"url": {
							"raw": "{{baseUrl}}/api/v1/islam/calendar/hijri-month?year=1447&month=9",
							"host": ["{{baseUrl}}"],
							"path": ["api", "v1", "islam", "calendar", "hijri-month"],
							"query": [
								{
									"key": "year",
									"value": "1447"
								},
								{
									"key": "month",
									"value": "9",
									"description": "Ramadan"
								},
								{
									"key": "timezone",
									"value": "Asia/Jakarta",
									"description": "IANA timezone (optional)",
									"disabled": true
								}
							]
						}
					},
					"response": []
				},
				{
					"name": "Get All Islamic Events",
					"request": {
						"method": "GET",
						"header": [],
						"url": {
							"raw": "{{baseUrl}}/api/v1/islam/calendar/events",
							"host": ["{{baseUrl}}"],
							"path": ["api", "v1", "islam", "calendar", "events"]
						}
					},
					"response": []
				},
				{
					"name": "Get Upcoming Events",
					"request": {
						"method": "GET",
						"header": [],
						"url": {
							"raw": "{{baseUrl}}/api/v1/islam/calendar/events/upcoming?days=90",
							"host": ["{{baseUrl}}"],
							"path": ["api", "v1", "islam", "calendar", "events", "upcoming"],
							"query": [
								{
									"key": "days",
									"value": "90"
								},
								{
									"key": "timezone",
									"value": "Europe/London",
									"description": "IANA timezone (optional)",
									"disabled": true
								}
							]
						}
					},
					"response": []
				},
				{
					"name": "Get Hijri Month Names",
					"request": {
						"method": "GET",
						"header": [],
						"url": {
							"raw": "{{baseUrl}}/api/v1/islam/calendar/months",
							"host": ["{{baseUrl}}"],
							"path": ["api", "v1", "islam", "calendar", "months"]
						}
					},
					"response": []
				}
			]
		},
		{
			"name": "Prayers",
			"item": [
				{
					"name": "Get Prayer Times",
					"request": {
						"method": "GET",
						"header": [],
						"url": {
							"raw": "{{baseUrl}}/api/v1/islam/prayers/times?lat=12.9716&lng=77.5946&date=2026-02-15",
							"host": ["{{baseUrl}}"],
							"path": ["api", "v1", "islam", "prayers", "times"],
							"query": [
								{
									"key": "lat",
									"value": "12.9716"
								},
								{
									"key": "lng",
									"value": "77.5946"
								},
								{
									"key": "date",
									"value": "2026-02-15"
								},
								{
									"key": "method",
									"value": "mwl",
									"disabled": true
								}
							]
						}
					},
					"response": []
				},
				{
					"name": "Get Current Prayer",
					"request": {
						"method": "GET",
						"header": [],
						"url": {
							"raw": "{{baseUrl}}/api/v1/islam/prayers/current?lat=12.9716&lng=77.5946",
							"host": ["{{baseUrl}}"],
							"path": ["api", "v1", "islam", "prayers", "current"],
							"query": [
								{
									"key": "lat",
									"value": "12.9716"
								},
								{
									"key": "lng",
									"value": "77.5946"
								}
							]
						}
					},
					"response": []
				},
				{
					"name": "Log Prayer",
					"request": {
						"auth": {
							"type": "bearer",
							"bearer": [
								{
									"key": "token",
									"value": "{{token}}",
									"type": "string"
								}
							]
						},
						"method": "POST",
						"header": [],
						"body": {
							"mode": "raw",
							"raw": "{\n    \"prayerName\": \"fajr\",\n    \"date\": \"2026-02-15\",\n    \"status\": \"on_time\"\n}",
							"options": {
								"raw": {
									"language": "json"
								}
							}
						},
						"url": {
							"raw": "{{baseUrl}}/api/v1/islam/prayers/log",
							"host": ["{{baseUrl}}"],
							"path": ["api", "v1", "islam", "prayers", "log"]
						}
					},
					"response": []
				},
				{
					"name": "Get Prayer Logs",
					"request": {
						"auth": {
							"type": "bearer",
							"bearer": [
								{
									"key": "token",
									"value": "{{token}}",
									"type": "string"
								}
							]
						},
						"method": "GET",
						"header": [],
						"url": {
							"raw": "{{baseUrl}}/api/v1/islam/prayers/logs",
							"host": ["{{baseUrl}}"],
							"path": ["api", "v1", "islam", "prayers", "logs"]
						}
					},
					"response": []
				},
				{
					"name": "Get Prayer Stats",
					"request": {
						"auth": {
							"type": "bearer",
							"bearer": [
								{
									"key": "token",
									"value": "{{token}}",
									"type": "string"
								}
							]
						},
						"method": "GET",
						"header": [],
						"url": {
							"raw": "{{baseUrl}}/api/v1/islam/prayers/stats",
							"host": ["{{baseUrl}}"],
							"path": ["api", "v1", "islam", "prayers", "stats"]
						}
					},
					"response": []
				}
			]
		},
		{
			"name": "Quran",
			"item": [
				{
					"name": "Get All Surahs",
					"request": {
						"method": "GET",
						"header": [],
						"url": {
							"raw": "{{baseUrl}}/api/v1/islam/quran/surahs",
							"host": ["{{baseUrl}}"],
							"path": ["api", "v1", "islam", "quran", "surahs"]
						}
					},
					"response": []
				},
				{
					"name": "Get Surah (Al-Fatihah)",
					"request": {
						"method": "GET",
						"header": [],
						"url": {
							"raw": "{{baseUrl}}/api/v1/islam/quran/surah/1",
							"host": ["{{baseUrl}}"],
							"path": ["api", "v1", "islam", "quran", "surah", "1"]
						}
					},
					"response": []
				},
				{
					"name": "Search Verses (Mercy)",
					"request": {
						"method": "GET",
						"header": [],
						"url": {
							"raw": "{{baseUrl}}/api/v1/islam/quran/search?q=mercy",
							"host": ["{{baseUrl}}"],
							"path": ["api", "v1", "islam", "quran", "search"],
							"query": [
								{
									"key": "q",
									"value": "mercy"
								}
							]
						}
					},
					"response": []
				},
				{
					"name": "Add Bookmark",
					"request": {
						"auth": {
							"type": "bearer",
							"bearer": [
								{
									"key": "token",
									"value": "{{token}}",
									"type": "string"
								}
							]
						},
						"method": "POST",
						"header": [],
						"body": {
							"mode": "raw",
							"raw": "{\n    \"surahId\": 1,\n    \"verseNumber\": 1,\n    \"note\": \"First verse\"\n}",
							"options": {
								"raw": {
									"language": "json"
								}
							}
						},
						"url": {
							"raw": "{{baseUrl}}/api/v1/islam/quran/bookmarks",
							"host": ["{{baseUrl}}"],
							"path": ["api", "v1", "islam", "quran", "bookmarks"]
						}
					},
					"response": []
				},
				{
					"name": "Get Bookmarks",
					"request": {
						"auth": {
							"type": "bearer",
							"bearer": [
								{
									"key": "token",
									"value": "{{token}}",
									"type": "string"
								}
							]
						},
						"method": "GET",
						"header": [],
						"url": {
							"raw": "{{baseUrl}}/api/v1/islam/quran/bookmarks",
							"host": ["{{baseUrl}}"],
							"path": ["api", "v1", "islam", "quran", "bookmarks"]
						}
					},
					"response": []
				}
			]
		},
		{
			"name": "Dhikr",
			"item": [
				{
					"name": "Get Counters",
					"request": {
						"auth": {
							"type": "bearer",
							"bearer": [
								{
									"key": "token",
									"value": "{{token}}",
									"type": "string"
								}
							]
						},
						"method": "GET",
						"header": [],
						"url": {
							"raw": "{{baseUrl}}/api/v1/islam/dhikr/counters",
							"host": ["{{baseUrl}}"],
							"path": ["api", "v1", "islam", "dhikr", "counters"]
						}
					},
					"response": []
				},
				{
					"name": "Create Counter",
					"event": [
						{
							"listen": "test",
							"script": {
								"exec": [
									"var jsonData = pm.response.json();",
									"if (jsonData.id) {",
									"    pm.environment.set(\"counterId\", jsonData.id);",
									"}"
								],
								"type": "text/javascript"
							}
						}
					],
					"request": {
						"auth": {
							"type": "bearer",
							"bearer": [
								{
									"key": "token",
									"value": "{{token}}",
									"type": "string"
								}
							]
						},
						"method": "POST",
						"header": [],
						"body": {
							"mode": "raw",
							"raw": "{\n    \"name\": \"Morning Dhikr\",\n    \"phrase\": \"Subhanallah\",\n    \"targetCount\": 100\n}",
							"options": {
								"raw": {
									"language": "json"
								}
							}
						},
						"url": {
							"raw": "{{baseUrl}}/api/v1/islam/dhikr/counters",
							"host": ["{{baseUrl}}"],
							"path": ["api", "v1", "islam", "dhikr", "counters"]
						}
					},
					"response": []
				},
				{
					"name": "Increment Counter",
					"request": {
						"auth": {
							"type": "bearer",
							"bearer": [
								{
									"key": "token",
									"value": "{{token}}",
									"type": "string"
								}
							]
						},
						"method": "PATCH",
						"header": [],
						"body": {
							"mode": "raw",
							"raw": "{\n    \"count\": 1\n}",
							"options": {
								"raw": {
									"language": "json"
								}
							}
						},
						"url": {
							"raw": "{{baseUrl}}/api/v1/islam/dhikr/counters/{{counterId}}",
							"host": ["{{baseUrl}}"],
							"path": ["api", "v1", "islam", "dhikr", "counters", "{{counterId}}"]
						}
					},
					"response": []
				},
				{
					"name": "Create Goal",
					"request": {
						"auth": {
							"type": "bearer",
							"bearer": [
								{
									"key": "token",
									"value": "{{token}}",
									"type": "string"
								}
							]
						},
						"method": "POST",
						"header": [],
						"body": {
							"mode": "raw",
							"raw": "{\n    \"phrase\": \"Alhamdulillah\",\n    \"targetCount\": 1000,\n    \"period\": \"weekly\"\n}",
							"options": {
								"raw": {
									"language": "json"
								}
							}
						},
						"url": {
							"raw": "{{baseUrl}}/api/v1/islam/dhikr/goals",
							"host": ["{{baseUrl}}"],
							"path": ["api", "v1", "islam", "dhikr", "goals"]
						}
					},
					"response": []
				},
				{
					"name": "Get Goals",
					"request": {
						"auth": {
							"type": "bearer",
							"bearer": [
								{
									"key": "token",
									"value": "{{token}}",
									"type": "string"
								}
							]
						},
						"method": "GET",
						"header": [],
						"url": {
							"raw": "{{baseUrl}}/api/v1/islam/dhikr/goals",
							"host": ["{{baseUrl}}"],
							"path": ["api", "v1", "islam", "dhikr", "goals"]
						}
					},
					"response": []
				},
				{
					"name": "Get Stats",
					"request": {
						"auth": {
							"type": "bearer",
							"bearer": [
								{
									"key": "token",
									"value": "{{token}}",
									"type": "string"
								}
							]
						},
						"method": "GET",
						"header": [],
						"url": {
							"raw": "{{baseUrl}}/api/v1/islam/dhikr/stats",
							"host": ["{{baseUrl}}"],
							"path": ["api", "v1", "islam", "dhikr", "stats"]
						}
					},
					"response": []
				}
			]
		},
		{
			"name": "Qibla",
			"item": [
				{
					"name": "Get Qibla Direction",
					"request": {
						"method": "GET",
						"header": [],
						"url": {
							"raw": "{{baseUrl}}/api/v1/islam/qibla?lat=12.9716&lng=77.5946",
							"host": ["{{baseUrl}}"],
							"path": ["api", "v1", "islam", "qibla"],
							"query": [
								{
									"key": "lat",
									"value": "12.9716"
								},
								{
									"key": "lng",
									"value": "77.5946"
								}
							]
						}
					},
					"response": []
				}
			]
		},
		{
			"name": "Names of Allah",
			"item": [
				{
					"name": "Get All Names",
					"request": {
						"method": "GET",
						"header": [],
						"url": {
							"raw": "{{baseUrl}}/api/v1/islam/names/allah",
							"host": ["{{baseUrl}}"],
							"path": ["api", "v1", "islam", "names", "allah"]
						}
					},
					"response": []
				},
				{
					"name": "Get Name by ID",
					"request": {
						"method": "GET",
						"header": [],
						"url": {
							"raw": "{{baseUrl}}/api/v1/islam/names/allah/1",
							"host": ["{{baseUrl}}"],
							"path": ["api", "v1", "islam", "names", "allah", "1"]
						}
					},
					"response": []
				},
				{
					"name": "Get Daily Name",
					"request": {
						"method": "GET",
						"header": [],
						"url": {
							"raw": "{{baseUrl}}/api/v1/islam/names/daily",
							"host": ["{{baseUrl}}"],
							"path": ["api", "v1", "islam", "names", "daily"]
						}
					},
					"response": []
				},
				{
					"name": "Add Favorite Name",
					"request": {
						"auth": {
							"type": "bearer",
							"bearer": [
								{
									"key": "token",
									"value": "{{token}}",
									"type": "string"
								}
							]
						},
						"method": "POST",
						"header": [],
						"body": {
							"mode": "raw",
							"raw": "{\n    \"nameId\": 1\n}",
							"options": {
								"raw": {
									"language": "json"
								}
							}
						},
						"url": {
							"raw": "{{baseUrl}}/api/v1/islam/names/favorites",
							"host": ["{{baseUrl}}"],
							"path": ["api", "v1", "islam", "names", "favorites"]
						}
					},
					"response": []
				}
			]
		},
		{
			"name": "Feelings",
			"item": [
				{
					"name": "Get All Emotions",
					"request": {
						"method": "GET",
						"header": [],
						"url": {
							"raw": "{{baseUrl}}/api/v1/islam/feelings",
							"host": ["{{baseUrl}}"],
							"path": ["api", "v1", "islam", "feelings"]
						}
					},
					"response": []
				},
				{
					"name": "Get Emotion Details",
					"request": {
						"method": "GET",
						"header": [],
						"url": {
							"raw": "{{baseUrl}}/api/v1/islam/feelings/anxious",
							"host": ["{{baseUrl}}"],
							"path": ["api", "v1", "islam", "feelings", "anxious"]
						}
					},
					"response": []
				}
			]
		}
	],
	"event": [
		{
			"listen": "prerequest",
			"script": {
				"type": "text/javascript",
				"exec": [""]
			}
		},
		{
			"listen": "test",
			"script": {
				"type": "text/javascript",
				"exec": [""]
			}
		}
	],
	"variable": [
		{
			"key": "baseUrl",
			"value": "http://localhost:8000",
			"type": "string"
		}
	]
}
